bkflow_feel/FEEL.lark
bkflow_feel/__init__.py
bkflow_feel/__version__.py
bkflow_feel/api.py
bkflow_feel/data_models.py
bkflow_feel/exceptions.py
bkflow_feel/parsers.py
bkflow_feel/transformer.py
bkflow_feel/utils.py
bkflow_feel/validators.py
bkflow_feel-1.2.0.dist-info/WHEEL
bkflow_feel-1.2.0.dist-info/METADATA
bkflow_feel-1.2.0.dist-info/RECORD
