Metadata-Version: 2.1
Name: bkflow-feel
Version: 1.2.0
Summary: A FEEL (Friendly Enough Expression Language) parser for Python
Author-email: normal-wls <weishi.swee@qq.com>
Requires-Dist: lark >=1.1.7,<2
Requires-Dist: python-dateutil <3
Requires-Dist: pytz <2024
Requires-Dist: pydantic <3
Requires-Dist: pytest >=7.0.1,<8 ; extra == "test"
Requires-Dist: pytest-benchmark[histogram] >=3.4.1,<4 ; extra == "test"
Project-URL: Home, https://github.com/TencentBlueKing/bkflow-feel
Provides-Extra: test
